odoo/addons/web_widget_datepicker_options/README.rst
odoo/addons/web_widget_datepicker_options/__init__.py
odoo/addons/web_widget_datepicker_options/__manifest__.py
odoo/addons/web_widget_datepicker_options/static/description/icon.png
odoo/addons/web_widget_datepicker_options/static/description/icon.svg
odoo/addons/web_widget_datepicker_options/static/src/js/datepicker.js
odoo/addons/web_widget_datepicker_options/views/assets.xml
odoo11_addon_web_widget_datepicker_options-11.0.1.0.1.dist-info/DESCRIPTION.rst
odoo11_addon_web_widget_datepicker_options-11.0.1.0.1.dist-info/METADATA
odoo11_addon_web_widget_datepicker_options-11.0.1.0.1.dist-info/RECORD
odoo11_addon_web_widget_datepicker_options-11.0.1.0.1.dist-info/WHEEL
odoo11_addon_web_widget_datepicker_options-11.0.1.0.1.dist-info/metadata.json
odoo11_addon_web_widget_datepicker_options-11.0.1.0.1.dist-info/top_level.txt
